pyinsteon/__init__.py
pyinsteon/__main__.py
pyinsteon/address.py
pyinsteon/commands.py
pyinsteon/constants.py
pyinsteon/default_link.py
pyinsteon/events.py
pyinsteon/listener_exception_handler.py
pyinsteon/run_tool.py
pyinsteon/subscriber_base.py
pyinsteon/topics.py
pyinsteon/utils.py
pyinsteon/x10_address.py
pyinsteon/aldb/__init__.py
pyinsteon/aldb/aldb.py
pyinsteon/aldb/aldb_base.py
pyinsteon/aldb/aldb_battery.py
pyinsteon/aldb/aldb_record.py
pyinsteon/aldb/mock_modem_aldb.py
pyinsteon/aldb/modem_aldb.py
pyinsteon/aldb/no_aldb.py
pyinsteon/config/__init__.py
pyinsteon/config/derived_property.py
pyinsteon/config/device_flag.py
pyinsteon/config/extended_property.py
pyinsteon/config/load_button.py
pyinsteon/config/modem_config.py
pyinsteon/config/momentary_delay.py
pyinsteon/config/op_flag_property.py
pyinsteon/config/op_flag_property_byte.py
pyinsteon/config/operating_flag.py
pyinsteon/config/radio_button.py
pyinsteon/config/ramp_rate.py
pyinsteon/config/relay_mode.py
pyinsteon/config/toggle_button.py
pyinsteon/data_types/__init__.py
pyinsteon/data_types/all_link_record_flags.py
pyinsteon/data_types/im_config_flags.py
pyinsteon/data_types/io_sensor_config_flags.py
pyinsteon/data_types/message_flags.py
pyinsteon/data_types/user_data.py
pyinsteon/device_types/__init__.py
pyinsteon/device_types/access_control.py
pyinsteon/device_types/battery_base.py
pyinsteon/device_types/climate_control.py
pyinsteon/device_types/device_base.py
pyinsteon/device_types/device_commands.py
pyinsteon/device_types/dimmable_lighting_control.py
pyinsteon/device_types/energy_management.py
pyinsteon/device_types/general_controller.py
pyinsteon/device_types/hub.py
pyinsteon/device_types/i3_base.py
pyinsteon/device_types/ipdb.py
pyinsteon/device_types/mock_modem.py
pyinsteon/device_types/modem_base.py
pyinsteon/device_types/on_off_controller_base.py
pyinsteon/device_types/on_off_responder_base.py
pyinsteon/device_types/open_close_controller_base.py
pyinsteon-1.6.4.dist-info/licenses/LICENSE.rst
pyinsteon-1.6.4.dist-info/METADATA
pyinsteon-1.6.4.dist-info/WHEEL
pyinsteon-1.6.4.dist-info/entry_points.txt
pyinsteon-1.6.4.dist-info/top_level.txt
pyinsteon-1.6.4.dist-info/RECORD
