Metadata-Version: 2.4
Name: pyinsteon
Version: 1.6.4
Summary: Open-source Insteon home automation module running on Python 3.
Author-email: The pyinsteon authors <pyinsteon@harrisnj.net>
License: MIT License
Project-URL: Source Code, https://github.com/pyinsteon/pyinsteon
Project-URL: Bug Reports, https://github.com/pyinsteon/pyinsteon/issues
Keywords: home,automation,insteon,python,python3
Platform: any
Classifier: Development Status :: 5 - Production/Stable
Classifier: Intended Audience :: Developers
Classifier: License :: OSI Approved :: Apache Software License
Classifier: Operating System :: OS Independent
Classifier: Programming Language :: Python :: 3.9
Classifier: Programming Language :: Python :: 3.10
Classifier: Programming Language :: Python :: 3.11
Classifier: Programming Language :: Python :: 3.12
Classifier: Topic :: Home Automation
Requires-Python: >=3.9.0
License-File: LICENSE.rst
Requires-Dist: pyserial
Requires-Dist: pyserial-asyncio-fast>=0.16
Requires-Dist: aiohttp
Requires-Dist: pypubsub
Requires-Dist: aiofiles
Requires-Dist: voluptuous
Dynamic: license-file
